nflow/__init__.py
nflow/job.py
nflow/nflow_operator.py
nflow/pipeline.py
nflow/resource.py
nflow/trigger.py
nflow/utils.py
nflow_client_sdk-0.1.0.dist-info/LICENSE
nflow_client_sdk-0.1.0.dist-info/METADATA
nflow_client_sdk-0.1.0.dist-info/WHEEL
nflow_client_sdk-0.1.0.dist-info/top_level.txt
nflow_client_sdk-0.1.0.dist-info/RECORD
